csvschemavalidation/__init__.py
csvschemavalidation/checker.py
csvschemavalidation/defaults.py
csvschemavalidation/definitions.py
csvschemavalidation/exceptions.py
csvschemavalidation/schema.json
csvschemavalidation/utilities.py
csvschemavalidation/validators/__init__.py
csvschemavalidation/validators/data_validators.py
csvschemavalidation/validators/header_validators.py
csvschemavalidation/validators/rfc4180_validators.py
csvschemavalidation/validators/types.py
csvschemavalidation-0.0.8.dist-info/LICENSE
csvschemavalidation-0.0.8.dist-info/METADATA
csvschemavalidation-0.0.8.dist-info/WHEEL
csvschemavalidation-0.0.8.dist-info/top_level.txt
csvschemavalidation-0.0.8.dist-info/RECORD
