Metadata-Version: 2.1
Name: csvschemavalidation
Version: 0.0.8
Summary: csvschemavalidation is an implementation of CSV Schema in Python.
Home-page: https://github.com/YasineNifa/PyCSVSchema
Author: Yassine Nifa
Author-email: yasine.nifa@gmail.com
License: MIT
Keywords: csv schema json jsonschema validation validator
Classifier: Development Status :: 3 - Alpha
Classifier: Intended Audience :: Developers
Classifier: Topic :: Software Development :: Libraries :: Python Modules
Classifier: Intended Audience :: Information Technology
Classifier: License :: OSI Approved :: MIT License
Classifier: Programming Language :: Python :: 3.5
Classifier: Programming Language :: Python :: 3.6
Classifier: Programming Language :: Python :: 3.7
Classifier: Programming Language :: Python :: 3.8
License-File: LICENSE
Requires-Dist: jsonschema
Requires-Dist: rfc3986
Requires-Dist: pycountry
